napatrackmater/CloudAutoEncoder.py
napatrackmater/DeepEmbeddedClustering.py
napatrackmater/Trackcomparator.py
napatrackmater/Trackmate.py
napatrackmater/Trackvector.py
napatrackmater/__init__.py
napatrackmater/_version.py
napatrackmater/clustering.py
napatrackmater/drift.py
napatrackmater/ergodicity.py
napatrackmater/fast_radius_regression.py
napatrackmater/fate_mapping.py
napatrackmater/homology.py
napatrackmater/pretrained.py
napatrackmater-5.8.9.dist-info/licenses/LICENSE
napatrackmater-5.8.9.dist-info/METADATA
napatrackmater-5.8.9.dist-info/WHEEL
napatrackmater-5.8.9.dist-info/top_level.txt
napatrackmater-5.8.9.dist-info/RECORD
