Metadata-Version: 2.4
Name: napatrackmater
Version: 5.8.9
Summary: Import Trackmate XML files for Track Visualization and analysis in Napari.
Home-page: https://github.com/Kapoorlabs-CAPED/napatrackmater
Author: Varun Kapoor, Mari Tolonen, Jakub Sedzinski
Author-email: randomaccessiblekapoor@gmail.com
License: BSD-3-Clause
Project-URL: Bug Tracker, https://github.com/Kapoorlabs-CAPED/napatrackmater/issues
Project-URL: Documentation, https://github.com/Kapoorlabs-CAPED/napatrackmater#README.md
Project-URL: Source Code, https://github.com/Kapoorlabs-CAPED/napatrackmater
Project-URL: User Support, https://github.com/Kapoorlabs-CAPED/napatrackmater/issues
Classifier: Development Status :: 2 - Pre-Alpha
Classifier: Framework :: napari
Classifier: Intended Audience :: Developers
Classifier: License :: OSI Approved :: BSD License
Classifier: Operating System :: OS Independent
Classifier: Programming Language :: Python
Classifier: Programming Language :: Python :: 3
Classifier: Programming Language :: Python :: 3 :: Only
Classifier: Programming Language :: Python :: 3.8
Classifier: Programming Language :: Python :: 3.9
Classifier: Programming Language :: Python :: 3.10
Classifier: Topic :: Scientific/Engineering :: Image Processing
Requires-Python: >=3.8
License-File: LICENSE
Requires-Dist: lxml
Requires-Dist: vollseg
Requires-Dist: napari
Requires-Dist: natsort
Requires-Dist: seaborn
Requires-Dist: kapoorlabs-lightning
Requires-Dist: lightning
Requires-Dist: trimesh
Requires-Dist: umap-learn
Requires-Dist: plotly
Requires-Dist: pymesh
Requires-Dist: torchsummary
Requires-Dist: statsmodels
Provides-Extra: testing
Requires-Dist: tox; extra == "testing"
Requires-Dist: pytest; extra == "testing"
Requires-Dist: pytest-cov; extra == "testing"
Requires-Dist: pytest-qt; extra == "testing"
Requires-Dist: napari; extra == "testing"
Requires-Dist: pyqt5; extra == "testing"
Dynamic: license-file
